kkw2401_bmi/bmi_class.py
kkw2401_bmi/bmi_module.py
kkw2401_bmi-0.0.0.2.dist-info/METADATA
kkw2401_bmi-0.0.0.2.dist-info/WHEEL
kkw2401_bmi-0.0.0.2.dist-info/top_level.txt
kkw2401_bmi-0.0.0.2.dist-info/RECORD
